odoo/addons/l10n_ch_fix_isr_reference/__init__.py
odoo/addons/l10n_ch_fix_isr_reference/__manifest__.py
odoo/addons/l10n_ch_fix_isr_reference/i18n/l10n_ch_fix_isr_reference.pot
odoo/addons/l10n_ch_fix_isr_reference/models/__init__.py
odoo/addons/l10n_ch_fix_isr_reference/models/invoice.py
odoo/addons/l10n_ch_fix_isr_reference/static/description/icon.png
odoo12_addon_l10n_ch_fix_isr_reference-12.0.1.0.0.99.dev5.dist-info/METADATA
odoo12_addon_l10n_ch_fix_isr_reference-12.0.1.0.0.99.dev5.dist-info/WHEEL
odoo12_addon_l10n_ch_fix_isr_reference-12.0.1.0.0.99.dev5.dist-info/top_level.txt
odoo12_addon_l10n_ch_fix_isr_reference-12.0.1.0.0.99.dev5.dist-info/RECORD
